torahcodes/D.py
torahcodes/TBC.py
torahcodes/__init__.py
torahcodes/baphomet.py
torahcodes/modules/__init__.py
torahcodes/modules/conversions.py
torahcodes/modules/query.py
torahcodes/modules/shemhemaphoresh.py
torahcodes/resources/data/WordsOfSelectedTexts_GematriaValues.csv
torahcodes/resources/data/WordsOfSelectedTexts_GematriaValues_EntireHebrewBible.csv
torahcodes/resources/data/__init__.py
torahcodes/resources/data/text_10Ikings.json
torahcodes/resources/data/text_11IIkings.json
torahcodes/resources/data/text_12isaiah.json
torahcodes/resources/data/text_13jeremiah.json
torahcodes/resources/data/text_14ezekiel.json
torahcodes/resources/data/text_15hosea.json
torahcodes/resources/data/text_16joel.json
torahcodes/resources/data/text_17amos.json
torahcodes/resources/data/text_18obadiah.json
torahcodes/resources/data/text_19jonah.json
torahcodes/resources/data/text_1genesis.json
torahcodes/resources/data/text_20micah.json
torahcodes/resources/data/text_21nahum.json
torahcodes/resources/data/text_22habakkuk.json
torahcodes/resources/data/text_23zephaniah.json
torahcodes/resources/data/text_24haggai.json
torahcodes/resources/data/text_25zechariah.json
torahcodes/resources/data/text_26malachi.json
torahcodes/resources/data/text_27psalms.json
torahcodes/resources/data/text_28proverbs.json
torahcodes/resources/data/text_29job.json
torahcodes/resources/data/text_2exodus.json
torahcodes/resources/data/text_30songofsongs.json
torahcodes/resources/data/text_31ruth.json
torahcodes/resources/data/text_32lamentations.json
torahcodes/resources/data/text_33ecclesiastes.json
torahcodes/resources/data/text_34esther.json
torahcodes/resources/data/text_35daniel.json
torahcodes/resources/data/text_36ezra.json
torahcodes/resources/data/text_37nehemiah.json
torahcodes/resources/data/text_38Ichronicles.json
torahcodes/resources/data/text_39IIchronicles.json
torahcodes/resources/data/text_3leviticus.json
torahcodes/resources/data/text_4numbers.json
torahcodes-1.0.10.dist-info/METADATA
torahcodes-1.0.10.dist-info/WHEEL
torahcodes-1.0.10.dist-info/entry_points.txt
torahcodes-1.0.10.dist-info/top_level.txt
torahcodes-1.0.10.dist-info/RECORD
