Metadata-Version: 2.1
Name: torahcodes
Version: 1.0.10
Summary: An understandable multilanguaje and multithreading bible codes . Study the Torah as never before Bible Codes python library . An understandable multilanguaje and multithreading bible codes . Study the Torah as never before
Home-page: 
Author: torahcodes
Author-email: 
Project-URL: Source, https://github.com/pedroelbanquero/torahcodespython
Keywords: torahcodes
Classifier: Development Status :: 5 - Production/Stable
Classifier: Intended Audience :: Developers
Classifier: License :: OSI Approved :: MIT License
Classifier: Programming Language :: Python :: 3
Classifier: Programming Language :: Python :: 3.6
Classifier: Programming Language :: Python :: 3.9
Requires-Python: >=3.6.0
Requires-Dist: configparser
Requires-Dist: deep-translator
Requires-Dist: lxml
Requires-Dist: python-hebrew-numbers
Requires-Dist: requests
